<?xml version="1.0" encoding="UTF-8"?>
<Etiquetas><Idioma id="en"><LB_Criterio>Report Settings</LB_Criterio><LB_CuentasporCobrar>Accounts Receivable</LB_CuentasporCobrar><LB_DoctosAplic>Documents Applied</LB_DoctosAplic><LB_DoctosSApl>Documents Unapplied</LB_DoctosSApl><LB_Documento>Document</LB_Documento><LB_FecFact>Invoice Date</LB_FecFact><LB_FecVenc>Maturity Date</LB_FecVenc><LB_FinRep>End Report</LB_FinRep><LB_Hora>Time</LB_Hora><LB_NumReg>Records</LB_NumReg><LB_Socio>Partner</LB_Socio><LB_SocioNegocio>Partner</LB_SocioNegocio><LB_TotalDoc>Document Total</LB_TotalDoc><LB_TotalMon>Currency Total</LB_TotalMon><LB_TransaccionSA>Transaction</LB_TransaccionSA><MSG_ErrGen>There are more than 5000 records found</MSG_ErrGen><LB_Cantidad>Quantity</LB_Cantidad><LB_Impuesto>Tax</LB_Impuesto><LB_Linea>Line</LB_Linea><LB_Obser>Comments</LB_Obser><LB_PrecioU>Unit Price</LB_PrecioU><LB_TotDoctCI>Total Document (Tax)</LB_TotDoctCI><LB_TotLinea>Line Total</LB_TotLinea><LB_TotSocio>Partner Total</LB_TotSocio></Idioma></Etiquetas>
