<?xml version="1.0" encoding="UTF-8"?>
<Etiquetas><Idioma id="es"><inicio>Inicio</inicio><favoritos>Favoritos</favoritos><compania>Compa&amp;ntilde;&amp;iacute;a</compania></Idioma><Idioma id="en"><LB_AnaSaldo>Balance Analysis</LB_AnaSaldo><LB_Apartado>Section</LB_Apartado><LB_Cobrador>Collector</LB_Cobrador><LB_Corriente>Current</LB_Corriente><LB_Creditos>Credits</LB_Creditos><LB_DatosReporte>Report Settings</LB_DatosReporte><LB_De>From</LB_De><LB_Debitos>Debits</LB_Debitos><LB_Documento>Document</LB_Documento><LB_EdoCta>Statement of Account by Address</LB_EdoCta><LB_FecVenc>Maturity Date</LB_FecVenc><LB_Hora>Time</LB_Hora><LB_LimCred>Credit Limit</LB_LimCred><LB_Morosidad>Moroseness</LB_Morosidad><LB_NRecl>Claim</LB_NRecl><LB_OC>PO</LB_OC><LB_OrdenRec>Order by Claims</LB_OrdenRec><LB_Ref>Ref.</LB_Ref><LB_Saldo>Balance</LB_Saldo><LB_SinVenc>Not Matured</LB_SinVenc><LB_Sucursal>Office</LB_Sucursal><LB_TituloH>SIF - Accounts Receivable</LB_TituloH><LB_VencSaldo>Balance Maturity</LB_VencSaldo><LB_omas>or more</LB_omas><MSG_FechasLim>Verify range dates</MSG_FechasLim><MSG_Pie>We have received the original invoices purchase orders for this statement and we accept as correct and definitive the balance reflecting this statement</MSG_Pie><TIT_EdoCta>Statement of Account</TIT_EdoCta><TIT_EdoCue>Partner Statement</TIT_EdoCue><compania>Enterprise</compania><favoritos>Favorites</favoritos><inicio>Start</inicio><LB_NoHaSidoAsig>There has not been assigned</LB_NoHaSidoAsig></Idioma></Etiquetas>
