<?xml version="1.0" encoding="UTF-8"?>
<Etiquetas><Idioma id="en"><LB_Ambos>Both</LB_Ambos><LB_ClasEmpr>Only Enterprise Classifications</LB_ClasEmpr><LB_ClasifFin>Final Classification</LB_ClasifFin><LB_ClasifIni>Initial Classification</LB_ClasifIni><LB_Clientes>Clients</LB_Clientes><LB_Cobrador>Collector</LB_Cobrador><LB_DatosRep>Report Settings</LB_DatosRep><LB_LstCobrador>Collectors List</LB_LstCobrador><LB_LstCobrxDir>Collector</LB_LstCobrxDir><LB_Proveedores>Suppliers</LB_Proveedores><LB_Socio_Fin>Final Partner</LB_Socio_Fin><LB_Socio_Ini>Initial Partner</LB_Socio_Ini><TIT_DirSocsClas>Partner Address not Classified</TIT_DirSocsClas><TIT_RepSalsClas>Accounts Receivable</TIT_RepSalsClas><TIT_SocsClas>Partners not Classified</TIT_SocsClas></Idioma></Etiquetas>
