<?xml version="1.0"?>
<?mso-application progid="Excel.Sheet"?>
<Workbook xmlns="urn:schemas-microsoft-com:office:spreadsheet"
 xmlns:o="urn:schemas-microsoft-com:office:office"
 xmlns:x="urn:schemas-microsoft-com:office:excel"
 xmlns:ss="urn:schemas-microsoft-com:office:spreadsheet"
 xmlns:c="urn:schemas-microsoft-com:office:component:spreadsheet"
 xmlns:html="http://www.w3.org/TR/REC-html40">
 <DocumentProperties xmlns="urn:schemas-microsoft-com:office:office">
  <Author>danim</Author>
  <LastAuthor>danim</LastAuthor>
  <Created>2005-04-06T15:29:24Z</Created>
  <LastSaved>2005-04-06T15:30:12Z</LastSaved>
  <Company>danim</Company>
  <Version>11.5606</Version>
 </DocumentProperties>
 <ExcelWorkbook xmlns="urn:schemas-microsoft-com:office:excel">
  <WindowHeight>10005</WindowHeight>
  <WindowWidth>10005</WindowWidth>
  <WindowTopX>120</WindowTopX>
  <WindowTopY>135</WindowTopY>
  <ProtectStructure>False</ProtectStructure>
  <ProtectWindows>False</ProtectWindows>
 </ExcelWorkbook>
 <Styles>
  <Style ss:ID="Default" ss:Name="Normal">
   <Alignment ss:Vertical="Bottom"/>
   <Borders/>
   <Font/>
   <Interior/>
   <NumberFormat/>
   <Protection/>
  </Style>
 </Styles>
 <Worksheet ss:Name="Sheet1">
  <Names>
   <NamedRange ss:Name="Print_Area" ss:RefersTo="=Sheet1!R1C1:R24C9"/>
   <NamedRange ss:Name="Print_Titles" ss:RefersTo="=Sheet1!C1,Sheet1!R1:R2"/>
  </Names>
  <Table ss:ExpandedColumnCount="11" ss:ExpandedRowCount="24" x:FullColumns="1"
   x:FullRows="1">
   <Row ss:AutoFitHeight="0">
    <Cell><Data ss:Type="Number">1</Data><NamedCell ss:Name="Print_Area"/><NamedCell
      ss:Name="Print_Titles"/></Cell>
    <Cell ss:Formula="=RC[-1]+1"><Data ss:Type="Number">2</Data><NamedCell
      ss:Name="Print_Titles"/><NamedCell ss:Name="Print_Area"/></Cell>
    <Cell ss:Formula="=RC[-1]+1"><Data ss:Type="Number">3</Data><NamedCell
      ss:Name="Print_Titles"/><NamedCell ss:Name="Print_Area"/></Cell>
    <Cell ss:Formula="=RC[-1]+1"><Data ss:Type="Number">4</Data><NamedCell
      ss:Name="Print_Titles"/><NamedCell ss:Name="Print_Area"/></Cell>
    <Cell ss:Formula="=RC[-1]+1"><Data ss:Type="Number">5</Data><NamedCell
      ss:Name="Print_Titles"/><NamedCell ss:Name="Print_Area"/></Cell>
    <Cell ss:Formula="=RC[-1]+1"><Data ss:Type="Number">6</Data><NamedCell
      ss:Name="Print_Titles"/><NamedCell ss:Name="Print_Area"/></Cell>
    <Cell ss:Formula="=RC[-1]+1"><Data ss:Type="Number">7</Data><NamedCell
      ss:Name="Print_Titles"/><NamedCell ss:Name="Print_Area"/></Cell>
    <Cell ss:Formula="=RC[-1]+1"><Data ss:Type="Number">8</Data><NamedCell
      ss:Name="Print_Titles"/><NamedCell ss:Name="Print_Area"/></Cell>
    <Cell ss:Formula="=RC[-1]+1"><Data ss:Type="Number">9</Data><NamedCell
      ss:Name="Print_Titles"/><NamedCell ss:Name="Print_Area"/></Cell>
    <Cell ss:Formula="=RC[-1]+1"><Data ss:Type="Number">10</Data><NamedCell
      ss:Name="Print_Titles"/></Cell>
    <Cell ss:Formula="=RC[-1]+1"><Data ss:Type="Number">11</Data><NamedCell
      ss:Name="Print_Titles"/></Cell>
   </Row>
   <Row ss:AutoFitHeight="0">
    <Cell ss:Formula="=R[-1]C+1"><Data ss:Type="Number">2</Data><NamedCell
      ss:Name="Print_Area"/><NamedCell ss:Name="Print_Titles"/></Cell>
    <Cell ss:Formula="=R[-1]C+1"><Data ss:Type="Number">3</Data><NamedCell
      ss:Name="Print_Titles"/><NamedCell ss:Name="Print_Area"/></Cell>
    <Cell ss:Formula="=R[-1]C+1"><Data ss:Type="Number">4</Data><NamedCell
      ss:Name="Print_Titles"/><NamedCell ss:Name="Print_Area"/></Cell>
    <Cell ss:Formula="=R[-1]C+1"><Data ss:Type="Number">5</Data><NamedCell
      ss:Name="Print_Titles"/><NamedCell ss:Name="Print_Area"/></Cell>
    <Cell ss:Formula="=R[-1]C+1"><Data ss:Type="Number">6</Data><NamedCell
      ss:Name="Print_Titles"/><NamedCell ss:Name="Print_Area"/></Cell>
    <Cell ss:Formula="=R[-1]C+1"><Data ss:Type="Number">7</Data><NamedCell
      ss:Name="Print_Titles"/><NamedCell ss:Name="Print_Area"/></Cell>
    <Cell ss:Formula="=R[-1]C+1"><Data ss:Type="Number">8</Data><NamedCell
      ss:Name="Print_Titles"/><NamedCell ss:Name="Print_Area"/></Cell>
    <Cell ss:Formula="=R[-1]C+1"><Data ss:Type="Number">9</Data><NamedCell
      ss:Name="Print_Titles"/><NamedCell ss:Name="Print_Area"/></Cell>
    <Cell ss:Formula="=R[-1]C+1"><Data ss:Type="Number">10</Data><NamedCell
      ss:Name="Print_Titles"/><NamedCell ss:Name="Print_Area"/></Cell>
    <Cell ss:Formula="=R[-1]C+1"><Data ss:Type="Number">11</Data><NamedCell
      ss:Name="Print_Titles"/></Cell>
    <Cell ss:Formula="=R[-1]C+1"><Data ss:Type="Number">12</Data><NamedCell
      ss:Name="Print_Titles"/></Cell>
   </Row>
   <Row ss:AutoFitHeight="0">
    <Cell ss:Formula="=R[-1]C+1"><Data ss:Type="Number">3</Data><NamedCell
      ss:Name="Print_Area"/><NamedCell ss:Name="Print_Titles"/></Cell>
    <Cell ss:Formula="=R[-1]C+1"><Data ss:Type="Number">4</Data><NamedCell
      ss:Name="Print_Area"/></Cell>
    <Cell ss:Formula="=R[-1]C+1"><Data ss:Type="Number">5</Data><NamedCell
      ss:Name="Print_Area"/></Cell>
    <Cell ss:Formula="=R[-1]C+1"><Data ss:Type="Number">6</Data><NamedCell
      ss:Name="Print_Area"/></Cell>
    <Cell ss:Formula="=R[-1]C+1"><Data ss:Type="Number">7</Data><NamedCell
      ss:Name="Print_Area"/></Cell>
    <Cell ss:Formula="=R[-1]C+1"><Data ss:Type="Number">8</Data><NamedCell
      ss:Name="Print_Area"/></Cell>
    <Cell ss:Formula="=R[-1]C+1"><Data ss:Type="Number">9</Data><NamedCell
      ss:Name="Print_Area"/></Cell>
    <Cell ss:Formula="=R[-1]C+1"><Data ss:Type="Number">10</Data><NamedCell
      ss:Name="Print_Area"/></Cell>
    <Cell ss:Formula="=R[-1]C+1"><Data ss:Type="Number">11</Data><NamedCell
      ss:Name="Print_Area"/></Cell>
    <Cell ss:Formula="=R[-1]C+1"><Data ss:Type="Number">12</Data></Cell>
    <Cell ss:Formula="=R[-1]C+1"><Data ss:Type="Number">13</Data></Cell>
   </Row>
   <Row ss:AutoFitHeight="0">
    <Cell ss:Formula="=R[-1]C+1"><Data ss:Type="Number">4</Data><NamedCell
      ss:Name="Print_Area"/><NamedCell ss:Name="Print_Titles"/></Cell>
    <Cell ss:Formula="=R[-1]C+1"><Data ss:Type="Number">5</Data><NamedCell
      ss:Name="Print_Area"/></Cell>
    <Cell ss:Formula="=R[-1]C+1"><Data ss:Type="Number">6</Data><NamedCell
      ss:Name="Print_Area"/></Cell>
    <Cell ss:Formula="=R[-1]C+1"><Data ss:Type="Number">7</Data><NamedCell
      ss:Name="Print_Area"/></Cell>
    <Cell ss:Formula="=R[-1]C+1"><Data ss:Type="Number">8</Data><NamedCell
      ss:Name="Print_Area"/></Cell>
    <Cell ss:Formula="=R[-1]C+1"><Data ss:Type="Number">9</Data><NamedCell
      ss:Name="Print_Area"/></Cell>
    <Cell ss:Formula="=R[-1]C+1"><Data ss:Type="Number">10</Data><NamedCell
      ss:Name="Print_Area"/></Cell>
    <Cell ss:Formula="=R[-1]C+1"><Data ss:Type="Number">11</Data><NamedCell
      ss:Name="Print_Area"/></Cell>
    <Cell ss:Formula="=R[-1]C+1"><Data ss:Type="Number">12</Data><NamedCell
      ss:Name="Print_Area"/></Cell>
    <Cell ss:Formula="=R[-1]C+1"><Data ss:Type="Number">13</Data></Cell>
    <Cell ss:Formula="=R[-1]C+1"><Data ss:Type="Number">14</Data></Cell>
   </Row>
   <Row ss:AutoFitHeight="0">
    <Cell ss:Formula="=R[-1]C+1"><Data ss:Type="Number">5</Data><NamedCell
      ss:Name="Print_Area"/><NamedCell ss:Name="Print_Titles"/></Cell>
    <Cell ss:Formula="=R[-1]C+1"><Data ss:Type="Number">6</Data><NamedCell
      ss:Name="Print_Area"/></Cell>
    <Cell ss:Formula="=R[-1]C+1"><Data ss:Type="Number">7</Data><NamedCell
      ss:Name="Print_Area"/></Cell>
    <Cell ss:Formula="=R[-1]C+1"><Data ss:Type="Number">8</Data><NamedCell
      ss:Name="Print_Area"/></Cell>
    <Cell ss:Formula="=R[-1]C+1"><Data ss:Type="Number">9</Data><NamedCell
      ss:Name="Print_Area"/></Cell>
    <Cell ss:Formula="=R[-1]C+1"><Data ss:Type="Number">10</Data><NamedCell
      ss:Name="Print_Area"/></Cell>
    <Cell ss:Formula="=R[-1]C+1"><Data ss:Type="Number">11</Data><NamedCell
      ss:Name="Print_Area"/></Cell>
    <Cell ss:Formula="=R[-1]C+1"><Data ss:Type="Number">12</Data><NamedCell
      ss:Name="Print_Area"/></Cell>
    <Cell ss:Formula="=R[-1]C+1"><Data ss:Type="Number">13</Data><NamedCell
      ss:Name="Print_Area"/></Cell>
    <Cell ss:Formula="=R[-1]C+1"><Data ss:Type="Number">14</Data></Cell>
    <Cell ss:Formula="=R[-1]C+1"><Data ss:Type="Number">15</Data></Cell>
   </Row>
   <Row ss:AutoFitHeight="0">
    <Cell ss:Formula="=R[-1]C+1"><Data ss:Type="Number">6</Data><NamedCell
      ss:Name="Print_Area"/><NamedCell ss:Name="Print_Titles"/></Cell>
    <Cell ss:Formula="=R[-1]C+1"><Data ss:Type="Number">7</Data><NamedCell
      ss:Name="Print_Area"/></Cell>
    <Cell ss:Formula="=R[-1]C+1"><Data ss:Type="Number">8</Data><NamedCell
      ss:Name="Print_Area"/></Cell>
    <Cell ss:Formula="=R[-1]C+1"><Data ss:Type="Number">9</Data><NamedCell
      ss:Name="Print_Area"/></Cell>
    <Cell ss:Formula="=R[-1]C+1"><Data ss:Type="Number">10</Data><NamedCell
      ss:Name="Print_Area"/></Cell>
    <Cell ss:Formula="=R[-1]C+1"><Data ss:Type="Number">11</Data><NamedCell
      ss:Name="Print_Area"/></Cell>
    <Cell ss:Formula="=R[-1]C+1"><Data ss:Type="Number">12</Data><NamedCell
      ss:Name="Print_Area"/></Cell>
    <Cell ss:Formula="=R[-1]C+1"><Data ss:Type="Number">13</Data><NamedCell
      ss:Name="Print_Area"/></Cell>
    <Cell ss:Formula="=R[-1]C+1"><Data ss:Type="Number">14</Data><NamedCell
      ss:Name="Print_Area"/></Cell>
    <Cell ss:Formula="=R[-1]C+1"><Data ss:Type="Number">15</Data></Cell>
    <Cell ss:Formula="=R[-1]C+1"><Data ss:Type="Number">16</Data></Cell>
   </Row>
   <Row ss:AutoFitHeight="0">
    <Cell ss:Formula="=R[-1]C+1"><Data ss:Type="Number">7</Data><NamedCell
      ss:Name="Print_Area"/><NamedCell ss:Name="Print_Titles"/></Cell>
    <Cell ss:Formula="=R[-1]C+1"><Data ss:Type="Number">8</Data><NamedCell
      ss:Name="Print_Area"/></Cell>
    <Cell ss:Formula="=R[-1]C+1"><Data ss:Type="Number">9</Data><NamedCell
      ss:Name="Print_Area"/></Cell>
    <Cell ss:Formula="=R[-1]C+1"><Data ss:Type="Number">10</Data><NamedCell
      ss:Name="Print_Area"/></Cell>
    <Cell ss:Formula="=R[-1]C+1"><Data ss:Type="Number">11</Data><NamedCell
      ss:Name="Print_Area"/></Cell>
    <Cell ss:Formula="=R[-1]C+1"><Data ss:Type="Number">12</Data><NamedCell
      ss:Name="Print_Area"/></Cell>
    <Cell ss:Formula="=R[-1]C+1"><Data ss:Type="Number">13</Data><NamedCell
      ss:Name="Print_Area"/></Cell>
    <Cell ss:Formula="=R[-1]C+1"><Data ss:Type="Number">14</Data><NamedCell
      ss:Name="Print_Area"/></Cell>
    <Cell ss:Formula="=R[-1]C+1"><Data ss:Type="Number">15</Data><NamedCell
      ss:Name="Print_Area"/></Cell>
    <Cell ss:Formula="=R[-1]C+1"><Data ss:Type="Number">16</Data></Cell>
    <Cell ss:Formula="=R[-1]C+1"><Data ss:Type="Number">17</Data></Cell>
   </Row>
   <Row ss:AutoFitHeight="0">
    <Cell ss:Formula="=R[-1]C+1"><Data ss:Type="Number">8</Data><NamedCell
      ss:Name="Print_Area"/><NamedCell ss:Name="Print_Titles"/></Cell>
    <Cell ss:Formula="=R[-1]C+1"><Data ss:Type="Number">9</Data><NamedCell
      ss:Name="Print_Area"/></Cell>
    <Cell ss:Formula="=R[-1]C+1"><Data ss:Type="Number">10</Data><NamedCell
      ss:Name="Print_Area"/></Cell>
    <Cell ss:Formula="=R[-1]C+1"><Data ss:Type="Number">11</Data><NamedCell
      ss:Name="Print_Area"/></Cell>
    <Cell ss:Formula="=R[-1]C+1"><Data ss:Type="Number">12</Data><NamedCell
      ss:Name="Print_Area"/></Cell>
    <Cell ss:Formula="=R[-1]C+1"><Data ss:Type="Number">13</Data><NamedCell
      ss:Name="Print_Area"/></Cell>
    <Cell ss:Formula="=R[-1]C+1"><Data ss:Type="Number">14</Data><NamedCell
      ss:Name="Print_Area"/></Cell>
    <Cell ss:Formula="=R[-1]C+1"><Data ss:Type="Number">15</Data><NamedCell
      ss:Name="Print_Area"/></Cell>
    <Cell ss:Formula="=R[-1]C+1"><Data ss:Type="Number">16</Data><NamedCell
      ss:Name="Print_Area"/></Cell>
    <Cell ss:Formula="=R[-1]C+1"><Data ss:Type="Number">17</Data></Cell>
    <Cell ss:Formula="=R[-1]C+1"><Data ss:Type="Number">18</Data></Cell>
   </Row>
   <Row ss:AutoFitHeight="0">
    <Cell ss:Formula="=R[-1]C+1"><Data ss:Type="Number">9</Data><NamedCell
      ss:Name="Print_Area"/><NamedCell ss:Name="Print_Titles"/></Cell>
    <Cell ss:Formula="=R[-1]C+1"><Data ss:Type="Number">10</Data><NamedCell
      ss:Name="Print_Area"/></Cell>
    <Cell ss:Formula="=R[-1]C+1"><Data ss:Type="Number">11</Data><NamedCell
      ss:Name="Print_Area"/></Cell>
    <Cell ss:Formula="=R[-1]C+1"><Data ss:Type="Number">12</Data><NamedCell
      ss:Name="Print_Area"/></Cell>
    <Cell ss:Formula="=R[-1]C+1"><Data ss:Type="Number">13</Data><NamedCell
      ss:Name="Print_Area"/></Cell>
    <Cell ss:Formula="=R[-1]C+1"><Data ss:Type="Number">14</Data><NamedCell
      ss:Name="Print_Area"/></Cell>
    <Cell ss:Formula="=R[-1]C+1"><Data ss:Type="Number">15</Data><NamedCell
      ss:Name="Print_Area"/></Cell>
    <Cell ss:Formula="=R[-1]C+1"><Data ss:Type="Number">16</Data><NamedCell
      ss:Name="Print_Area"/></Cell>
    <Cell ss:Formula="=R[-1]C+1"><Data ss:Type="Number">17</Data><NamedCell
      ss:Name="Print_Area"/></Cell>
    <Cell ss:Formula="=R[-1]C+1"><Data ss:Type="Number">18</Data></Cell>
    <Cell ss:Formula="=R[-1]C+1"><Data ss:Type="Number">19</Data></Cell>
   </Row>
   <Row ss:AutoFitHeight="0">
    <Cell ss:Formula="=R[-1]C+1"><Data ss:Type="Number">10</Data><NamedCell
      ss:Name="Print_Area"/><NamedCell ss:Name="Print_Titles"/></Cell>
    <Cell ss:Formula="=R[-1]C+1"><Data ss:Type="Number">11</Data><NamedCell
      ss:Name="Print_Area"/></Cell>
    <Cell ss:Formula="=R[-1]C+1"><Data ss:Type="Number">12</Data><NamedCell
      ss:Name="Print_Area"/></Cell>
    <Cell ss:Formula="=R[-1]C+1"><Data ss:Type="Number">13</Data><NamedCell
      ss:Name="Print_Area"/></Cell>
    <Cell ss:Formula="=R[-1]C+1"><Data ss:Type="Number">14</Data><NamedCell
      ss:Name="Print_Area"/></Cell>
    <Cell ss:Formula="=R[-1]C+1"><Data ss:Type="Number">15</Data><NamedCell
      ss:Name="Print_Area"/></Cell>
    <Cell ss:Formula="=R[-1]C+1"><Data ss:Type="Number">16</Data><NamedCell
      ss:Name="Print_Area"/></Cell>
    <Cell ss:Formula="=R[-1]C+1"><Data ss:Type="Number">17</Data><NamedCell
      ss:Name="Print_Area"/></Cell>
    <Cell ss:Formula="=R[-1]C+1"><Data ss:Type="Number">18</Data><NamedCell
      ss:Name="Print_Area"/></Cell>
    <Cell ss:Formula="=R[-1]C+1"><Data ss:Type="Number">19</Data></Cell>
    <Cell ss:Formula="=R[-1]C+1"><Data ss:Type="Number">20</Data></Cell>
   </Row>
   <Row ss:AutoFitHeight="0">
    <Cell ss:Formula="=R[-1]C+1"><Data ss:Type="Number">11</Data><NamedCell
      ss:Name="Print_Area"/><NamedCell ss:Name="Print_Titles"/></Cell>
    <Cell ss:Formula="=R[-1]C+1"><Data ss:Type="Number">12</Data><NamedCell
      ss:Name="Print_Area"/></Cell>
    <Cell ss:Formula="=R[-1]C+1"><Data ss:Type="Number">13</Data><NamedCell
      ss:Name="Print_Area"/></Cell>
    <Cell ss:Formula="=R[-1]C+1"><Data ss:Type="Number">14</Data><NamedCell
      ss:Name="Print_Area"/></Cell>
    <Cell ss:Formula="=R[-1]C+1"><Data ss:Type="Number">15</Data><NamedCell
      ss:Name="Print_Area"/></Cell>
    <Cell ss:Formula="=R[-1]C+1"><Data ss:Type="Number">16</Data><NamedCell
      ss:Name="Print_Area"/></Cell>
    <Cell ss:Formula="=R[-1]C+1"><Data ss:Type="Number">17</Data><NamedCell
      ss:Name="Print_Area"/></Cell>
    <Cell ss:Formula="=R[-1]C+1"><Data ss:Type="Number">18</Data><NamedCell
      ss:Name="Print_Area"/></Cell>
    <Cell ss:Formula="=R[-1]C+1"><Data ss:Type="Number">19</Data><NamedCell
      ss:Name="Print_Area"/></Cell>
    <Cell ss:Formula="=R[-1]C+1"><Data ss:Type="Number">20</Data></Cell>
    <Cell ss:Formula="=R[-1]C+1"><Data ss:Type="Number">21</Data></Cell>
   </Row>
   <Row ss:AutoFitHeight="0">
    <Cell ss:Formula="=R[-1]C+1"><Data ss:Type="Number">12</Data><NamedCell
      ss:Name="Print_Area"/><NamedCell ss:Name="Print_Titles"/></Cell>
    <Cell ss:Formula="=R[-1]C+1"><Data ss:Type="Number">13</Data><NamedCell
      ss:Name="Print_Area"/></Cell>
    <Cell ss:Formula="=R[-1]C+1"><Data ss:Type="Number">14</Data><NamedCell
      ss:Name="Print_Area"/></Cell>
    <Cell ss:Formula="=R[-1]C+1"><Data ss:Type="Number">15</Data><NamedCell
      ss:Name="Print_Area"/></Cell>
    <Cell ss:Formula="=R[-1]C+1"><Data ss:Type="Number">16</Data><NamedCell
      ss:Name="Print_Area"/></Cell>
    <Cell ss:Formula="=R[-1]C+1"><Data ss:Type="Number">17</Data><NamedCell
      ss:Name="Print_Area"/></Cell>
    <Cell ss:Formula="=R[-1]C+1"><Data ss:Type="Number">18</Data><NamedCell
      ss:Name="Print_Area"/></Cell>
    <Cell ss:Formula="=R[-1]C+1"><Data ss:Type="Number">19</Data><NamedCell
      ss:Name="Print_Area"/></Cell>
    <Cell ss:Formula="=R[-1]C+1"><Data ss:Type="Number">20</Data><NamedCell
      ss:Name="Print_Area"/></Cell>
    <Cell ss:Formula="=R[-1]C+1"><Data ss:Type="Number">21</Data></Cell>
    <Cell ss:Formula="=R[-1]C+1"><Data ss:Type="Number">22</Data></Cell>
   </Row>
   <Row ss:AutoFitHeight="0">
    <Cell ss:Formula="=R[-1]C+1"><Data ss:Type="Number">13</Data><NamedCell
      ss:Name="Print_Area"/><NamedCell ss:Name="Print_Titles"/></Cell>
    <Cell ss:Formula="=R[-1]C+1"><Data ss:Type="Number">14</Data><NamedCell
      ss:Name="Print_Area"/></Cell>
    <Cell ss:Formula="=R[-1]C+1"><Data ss:Type="Number">15</Data><NamedCell
      ss:Name="Print_Area"/></Cell>
    <Cell ss:Formula="=R[-1]C+1"><Data ss:Type="Number">16</Data><NamedCell
      ss:Name="Print_Area"/></Cell>
    <Cell ss:Formula="=R[-1]C+1"><Data ss:Type="Number">17</Data><NamedCell
      ss:Name="Print_Area"/></Cell>
    <Cell ss:Formula="=R[-1]C+1"><Data ss:Type="Number">18</Data><NamedCell
      ss:Name="Print_Area"/></Cell>
    <Cell ss:Formula="=R[-1]C+1"><Data ss:Type="Number">19</Data><NamedCell
      ss:Name="Print_Area"/></Cell>
    <Cell ss:Formula="=R[-1]C+1"><Data ss:Type="Number">20</Data><NamedCell
      ss:Name="Print_Area"/></Cell>
    <Cell ss:Formula="=R[-1]C+1"><Data ss:Type="Number">21</Data><NamedCell
      ss:Name="Print_Area"/></Cell>
    <Cell ss:Formula="=R[-1]C+1"><Data ss:Type="Number">22</Data></Cell>
    <Cell ss:Formula="=R[-1]C+1"><Data ss:Type="Number">23</Data></Cell>
   </Row>
   <Row ss:AutoFitHeight="0">
    <Cell ss:Formula="=R[-1]C+1"><Data ss:Type="Number">14</Data><NamedCell
      ss:Name="Print_Area"/><NamedCell ss:Name="Print_Titles"/></Cell>
    <Cell ss:Formula="=R[-1]C+1"><Data ss:Type="Number">15</Data><NamedCell
      ss:Name="Print_Area"/></Cell>
    <Cell ss:Formula="=R[-1]C+1"><Data ss:Type="Number">16</Data><NamedCell
      ss:Name="Print_Area"/></Cell>
    <Cell ss:Formula="=R[-1]C+1"><Data ss:Type="Number">17</Data><NamedCell
      ss:Name="Print_Area"/></Cell>
    <Cell ss:Formula="=R[-1]C+1"><Data ss:Type="Number">18</Data><NamedCell
      ss:Name="Print_Area"/></Cell>
    <Cell ss:Formula="=R[-1]C+1"><Data ss:Type="Number">19</Data><NamedCell
      ss:Name="Print_Area"/></Cell>
    <Cell ss:Formula="=R[-1]C+1"><Data ss:Type="Number">20</Data><NamedCell
      ss:Name="Print_Area"/></Cell>
    <Cell ss:Formula="=R[-1]C+1"><Data ss:Type="Number">21</Data><NamedCell
      ss:Name="Print_Area"/></Cell>
    <Cell ss:Formula="=R[-1]C+1"><Data ss:Type="Number">22</Data><NamedCell
      ss:Name="Print_Area"/></Cell>
    <Cell ss:Formula="=R[-1]C+1"><Data ss:Type="Number">23</Data></Cell>
    <Cell ss:Formula="=R[-1]C+1"><Data ss:Type="Number">24</Data></Cell>
   </Row>
   <Row ss:AutoFitHeight="0">
    <Cell ss:Formula="=R[-1]C+1"><Data ss:Type="Number">15</Data><NamedCell
      ss:Name="Print_Area"/><NamedCell ss:Name="Print_Titles"/></Cell>
    <Cell ss:Formula="=R[-1]C+1"><Data ss:Type="Number">16</Data><NamedCell
      ss:Name="Print_Area"/></Cell>
    <Cell ss:Formula="=R[-1]C+1"><Data ss:Type="Number">17</Data><NamedCell
      ss:Name="Print_Area"/></Cell>
    <Cell ss:Formula="=R[-1]C+1"><Data ss:Type="Number">18</Data><NamedCell
      ss:Name="Print_Area"/></Cell>
    <Cell ss:Formula="=R[-1]C+1"><Data ss:Type="Number">19</Data><NamedCell
      ss:Name="Print_Area"/></Cell>
    <Cell ss:Formula="=R[-1]C+1"><Data ss:Type="Number">20</Data><NamedCell
      ss:Name="Print_Area"/></Cell>
    <Cell ss:Formula="=R[-1]C+1"><Data ss:Type="Number">21</Data><NamedCell
      ss:Name="Print_Area"/></Cell>
    <Cell ss:Formula="=R[-1]C+1"><Data ss:Type="Number">22</Data><NamedCell
      ss:Name="Print_Area"/></Cell>
    <Cell ss:Formula="=R[-1]C+1"><Data ss:Type="Number">23</Data><NamedCell
      ss:Name="Print_Area"/></Cell>
    <Cell ss:Formula="=R[-1]C+1"><Data ss:Type="Number">24</Data></Cell>
    <Cell ss:Formula="=R[-1]C+1"><Data ss:Type="Number">25</Data></Cell>
   </Row>
   <Row ss:AutoFitHeight="0">
    <Cell ss:Formula="=R[-1]C+1"><Data ss:Type="Number">16</Data><NamedCell
      ss:Name="Print_Area"/><NamedCell ss:Name="Print_Titles"/></Cell>
    <Cell ss:Formula="=R[-1]C+1"><Data ss:Type="Number">17</Data><NamedCell
      ss:Name="Print_Area"/></Cell>
    <Cell ss:Formula="=R[-1]C+1"><Data ss:Type="Number">18</Data><NamedCell
      ss:Name="Print_Area"/></Cell>
    <Cell ss:Formula="=R[-1]C+1"><Data ss:Type="Number">19</Data><NamedCell
      ss:Name="Print_Area"/></Cell>
    <Cell ss:Formula="=R[-1]C+1"><Data ss:Type="Number">20</Data><NamedCell
      ss:Name="Print_Area"/></Cell>
    <Cell ss:Formula="=R[-1]C+1"><Data ss:Type="Number">21</Data><NamedCell
      ss:Name="Print_Area"/></Cell>
    <Cell ss:Formula="=R[-1]C+1"><Data ss:Type="Number">22</Data><NamedCell
      ss:Name="Print_Area"/></Cell>
    <Cell ss:Formula="=R[-1]C+1"><Data ss:Type="Number">23</Data><NamedCell
      ss:Name="Print_Area"/></Cell>
    <Cell ss:Formula="=R[-1]C+1"><Data ss:Type="Number">24</Data><NamedCell
      ss:Name="Print_Area"/></Cell>
    <Cell ss:Formula="=R[-1]C+1"><Data ss:Type="Number">25</Data></Cell>
    <Cell ss:Formula="=R[-1]C+1"><Data ss:Type="Number">26</Data></Cell>
   </Row>
   <Row ss:AutoFitHeight="0">
    <Cell ss:Formula="=R[-1]C+1"><Data ss:Type="Number">17</Data><NamedCell
      ss:Name="Print_Area"/><NamedCell ss:Name="Print_Titles"/></Cell>
    <Cell ss:Formula="=R[-1]C+1"><Data ss:Type="Number">18</Data><NamedCell
      ss:Name="Print_Area"/></Cell>
    <Cell ss:Formula="=R[-1]C+1"><Data ss:Type="Number">19</Data><NamedCell
      ss:Name="Print_Area"/></Cell>
    <Cell ss:Formula="=R[-1]C+1"><Data ss:Type="Number">20</Data><NamedCell
      ss:Name="Print_Area"/></Cell>
    <Cell ss:Formula="=R[-1]C+1"><Data ss:Type="Number">21</Data><NamedCell
      ss:Name="Print_Area"/></Cell>
    <Cell ss:Formula="=R[-1]C+1"><Data ss:Type="Number">22</Data><NamedCell
      ss:Name="Print_Area"/></Cell>
    <Cell ss:Formula="=R[-1]C+1"><Data ss:Type="Number">23</Data><NamedCell
      ss:Name="Print_Area"/></Cell>
    <Cell ss:Formula="=R[-1]C+1"><Data ss:Type="Number">24</Data><NamedCell
      ss:Name="Print_Area"/></Cell>
    <Cell ss:Formula="=R[-1]C+1"><Data ss:Type="Number">25</Data><NamedCell
      ss:Name="Print_Area"/></Cell>
    <Cell ss:Formula="=R[-1]C+1"><Data ss:Type="Number">26</Data></Cell>
    <Cell ss:Formula="=R[-1]C+1"><Data ss:Type="Number">27</Data></Cell>
   </Row>
   <Row ss:AutoFitHeight="0">
    <Cell ss:Formula="=R[-1]C+1"><Data ss:Type="Number">18</Data><NamedCell
      ss:Name="Print_Area"/><NamedCell ss:Name="Print_Titles"/></Cell>
    <Cell ss:Formula="=R[-1]C+1"><Data ss:Type="Number">19</Data><NamedCell
      ss:Name="Print_Area"/></Cell>
    <Cell ss:Formula="=R[-1]C+1"><Data ss:Type="Number">20</Data><NamedCell
      ss:Name="Print_Area"/></Cell>
    <Cell ss:Formula="=R[-1]C+1"><Data ss:Type="Number">21</Data><NamedCell
      ss:Name="Print_Area"/></Cell>
    <Cell ss:Formula="=R[-1]C+1"><Data ss:Type="Number">22</Data><NamedCell
      ss:Name="Print_Area"/></Cell>
    <Cell ss:Formula="=R[-1]C+1"><Data ss:Type="Number">23</Data><NamedCell
      ss:Name="Print_Area"/></Cell>
    <Cell ss:Formula="=R[-1]C+1"><Data ss:Type="Number">24</Data><NamedCell
      ss:Name="Print_Area"/></Cell>
    <Cell ss:Formula="=R[-1]C+1"><Data ss:Type="Number">25</Data><NamedCell
      ss:Name="Print_Area"/></Cell>
    <Cell ss:Formula="=R[-1]C+1"><Data ss:Type="Number">26</Data><NamedCell
      ss:Name="Print_Area"/></Cell>
    <Cell ss:Formula="=R[-1]C+1"><Data ss:Type="Number">27</Data></Cell>
    <Cell ss:Formula="=R[-1]C+1"><Data ss:Type="Number">28</Data></Cell>
   </Row>
   <Row ss:AutoFitHeight="0">
    <Cell ss:Formula="=R[-1]C+1"><Data ss:Type="Number">19</Data><NamedCell
      ss:Name="Print_Area"/><NamedCell ss:Name="Print_Titles"/></Cell>
    <Cell ss:Formula="=R[-1]C+1"><Data ss:Type="Number">20</Data><NamedCell
      ss:Name="Print_Area"/></Cell>
    <Cell ss:Formula="=R[-1]C+1"><Data ss:Type="Number">21</Data><NamedCell
      ss:Name="Print_Area"/></Cell>
    <Cell ss:Formula="=R[-1]C+1"><Data ss:Type="Number">22</Data><NamedCell
      ss:Name="Print_Area"/></Cell>
    <Cell ss:Formula="=R[-1]C+1"><Data ss:Type="Number">23</Data><NamedCell
      ss:Name="Print_Area"/></Cell>
    <Cell ss:Formula="=R[-1]C+1"><Data ss:Type="Number">24</Data><NamedCell
      ss:Name="Print_Area"/></Cell>
    <Cell ss:Formula="=R[-1]C+1"><Data ss:Type="Number">25</Data><NamedCell
      ss:Name="Print_Area"/></Cell>
    <Cell ss:Formula="=R[-1]C+1"><Data ss:Type="Number">26</Data><NamedCell
      ss:Name="Print_Area"/></Cell>
    <Cell ss:Formula="=R[-1]C+1"><Data ss:Type="Number">27</Data><NamedCell
      ss:Name="Print_Area"/></Cell>
    <Cell ss:Formula="=R[-1]C+1"><Data ss:Type="Number">28</Data></Cell>
    <Cell ss:Formula="=R[-1]C+1"><Data ss:Type="Number">29</Data></Cell>
   </Row>
   <Row ss:AutoFitHeight="0">
    <Cell ss:Formula="=R[-1]C+1"><Data ss:Type="Number">20</Data><NamedCell
      ss:Name="Print_Area"/><NamedCell ss:Name="Print_Titles"/></Cell>
    <Cell ss:Formula="=R[-1]C+1"><Data ss:Type="Number">21</Data><NamedCell
      ss:Name="Print_Area"/></Cell>
    <Cell ss:Formula="=R[-1]C+1"><Data ss:Type="Number">22</Data><NamedCell
      ss:Name="Print_Area"/></Cell>
    <Cell ss:Formula="=R[-1]C+1"><Data ss:Type="Number">23</Data><NamedCell
      ss:Name="Print_Area"/></Cell>
    <Cell ss:Formula="=R[-1]C+1"><Data ss:Type="Number">24</Data><NamedCell
      ss:Name="Print_Area"/></Cell>
    <Cell ss:Formula="=R[-1]C+1"><Data ss:Type="Number">25</Data><NamedCell
      ss:Name="Print_Area"/></Cell>
    <Cell ss:Formula="=R[-1]C+1"><Data ss:Type="Number">26</Data><NamedCell
      ss:Name="Print_Area"/></Cell>
    <Cell ss:Formula="=R[-1]C+1"><Data ss:Type="Number">27</Data><NamedCell
      ss:Name="Print_Area"/></Cell>
    <Cell ss:Formula="=R[-1]C+1"><Data ss:Type="Number">28</Data><NamedCell
      ss:Name="Print_Area"/></Cell>
    <Cell ss:Formula="=R[-1]C+1"><Data ss:Type="Number">29</Data></Cell>
    <Cell ss:Formula="=R[-1]C+1"><Data ss:Type="Number">30</Data></Cell>
   </Row>
   <Row ss:AutoFitHeight="0">
    <Cell ss:Formula="=R[-1]C+1"><Data ss:Type="Number">21</Data><NamedCell
      ss:Name="Print_Area"/><NamedCell ss:Name="Print_Titles"/></Cell>
    <Cell ss:Formula="=R[-1]C+1"><Data ss:Type="Number">22</Data><NamedCell
      ss:Name="Print_Area"/></Cell>
    <Cell ss:Formula="=R[-1]C+1"><Data ss:Type="Number">23</Data><NamedCell
      ss:Name="Print_Area"/></Cell>
    <Cell ss:Formula="=R[-1]C+1"><Data ss:Type="Number">24</Data><NamedCell
      ss:Name="Print_Area"/></Cell>
    <Cell ss:Formula="=R[-1]C+1"><Data ss:Type="Number">25</Data><NamedCell
      ss:Name="Print_Area"/></Cell>
    <Cell ss:Formula="=R[-1]C+1"><Data ss:Type="Number">26</Data><NamedCell
      ss:Name="Print_Area"/></Cell>
    <Cell ss:Formula="=R[-1]C+1"><Data ss:Type="Number">27</Data><NamedCell
      ss:Name="Print_Area"/></Cell>
    <Cell ss:Formula="=R[-1]C+1"><Data ss:Type="Number">28</Data><NamedCell
      ss:Name="Print_Area"/></Cell>
    <Cell ss:Formula="=R[-1]C+1"><Data ss:Type="Number">29</Data><NamedCell
      ss:Name="Print_Area"/></Cell>
    <Cell ss:Formula="=R[-1]C+1"><Data ss:Type="Number">30</Data></Cell>
    <Cell ss:Formula="=R[-1]C+1"><Data ss:Type="Number">31</Data></Cell>
   </Row>
   <Row ss:AutoFitHeight="0">
    <Cell ss:Formula="=R[-1]C+1"><Data ss:Type="Number">22</Data><NamedCell
      ss:Name="Print_Area"/><NamedCell ss:Name="Print_Titles"/></Cell>
    <Cell ss:Formula="=R[-1]C+1"><Data ss:Type="Number">23</Data><NamedCell
      ss:Name="Print_Area"/></Cell>
    <Cell ss:Formula="=R[-1]C+1"><Data ss:Type="Number">24</Data><NamedCell
      ss:Name="Print_Area"/></Cell>
    <Cell ss:Formula="=R[-1]C+1"><Data ss:Type="Number">25</Data><NamedCell
      ss:Name="Print_Area"/></Cell>
    <Cell ss:Formula="=R[-1]C+1"><Data ss:Type="Number">26</Data><NamedCell
      ss:Name="Print_Area"/></Cell>
    <Cell ss:Formula="=R[-1]C+1"><Data ss:Type="Number">27</Data><NamedCell
      ss:Name="Print_Area"/></Cell>
    <Cell ss:Formula="=R[-1]C+1"><Data ss:Type="Number">28</Data><NamedCell
      ss:Name="Print_Area"/></Cell>
    <Cell ss:Formula="=R[-1]C+1"><Data ss:Type="Number">29</Data><NamedCell
      ss:Name="Print_Area"/></Cell>
    <Cell ss:Formula="=R[-1]C+1"><Data ss:Type="Number">30</Data><NamedCell
      ss:Name="Print_Area"/></Cell>
    <Cell ss:Formula="=R[-1]C+1"><Data ss:Type="Number">31</Data></Cell>
    <Cell ss:Formula="=R[-1]C+1"><Data ss:Type="Number">32</Data></Cell>
   </Row>
   <Row ss:AutoFitHeight="0">
    <Cell ss:Formula="=R[-1]C+1"><Data ss:Type="Number">23</Data><NamedCell
      ss:Name="Print_Area"/><NamedCell ss:Name="Print_Titles"/></Cell>
    <Cell ss:Formula="=R[-1]C+1"><Data ss:Type="Number">24</Data><NamedCell
      ss:Name="Print_Area"/></Cell>
    <Cell ss:Formula="=R[-1]C+1"><Data ss:Type="Number">25</Data><NamedCell
      ss:Name="Print_Area"/></Cell>
    <Cell ss:Formula="=R[-1]C+1"><Data ss:Type="Number">26</Data><NamedCell
      ss:Name="Print_Area"/></Cell>
    <Cell ss:Formula="=R[-1]C+1"><Data ss:Type="Number">27</Data><NamedCell
      ss:Name="Print_Area"/></Cell>
    <Cell ss:Formula="=R[-1]C+1"><Data ss:Type="Number">28</Data><NamedCell
      ss:Name="Print_Area"/></Cell>
    <Cell ss:Formula="=R[-1]C+1"><Data ss:Type="Number">29</Data><NamedCell
      ss:Name="Print_Area"/></Cell>
    <Cell ss:Formula="=R[-1]C+1"><Data ss:Type="Number">30</Data><NamedCell
      ss:Name="Print_Area"/></Cell>
    <Cell ss:Formula="=R[-1]C+1"><Data ss:Type="Number">31</Data><NamedCell
      ss:Name="Print_Area"/></Cell>
    <Cell ss:Formula="=R[-1]C+1"><Data ss:Type="Number">32</Data></Cell>
    <Cell ss:Formula="=R[-1]C+1"><Data ss:Type="Number">33</Data></Cell>
   </Row>
   <Row ss:AutoFitHeight="0">
    <Cell ss:Formula="=R[-1]C+1"><Data ss:Type="Number">24</Data><NamedCell
      ss:Name="Print_Area"/><NamedCell ss:Name="Print_Titles"/></Cell>
    <Cell ss:Formula="=R[-1]C+1"><Data ss:Type="Number">25</Data><NamedCell
      ss:Name="Print_Area"/></Cell>
    <Cell ss:Formula="=R[-1]C+1"><Data ss:Type="Number">26</Data><NamedCell
      ss:Name="Print_Area"/></Cell>
    <Cell ss:Formula="=R[-1]C+1"><Data ss:Type="Number">27</Data><NamedCell
      ss:Name="Print_Area"/></Cell>
    <Cell ss:Formula="=R[-1]C+1"><Data ss:Type="Number">28</Data><NamedCell
      ss:Name="Print_Area"/></Cell>
    <Cell ss:Formula="=R[-1]C+1"><Data ss:Type="Number">29</Data><NamedCell
      ss:Name="Print_Area"/></Cell>
    <Cell ss:Formula="=R[-1]C+1"><Data ss:Type="Number">30</Data><NamedCell
      ss:Name="Print_Area"/></Cell>
    <Cell ss:Formula="=R[-1]C+1"><Data ss:Type="Number">31</Data><NamedCell
      ss:Name="Print_Area"/></Cell>
    <Cell ss:Formula="=R[-1]C+1"><Data ss:Type="Number">32</Data><NamedCell
      ss:Name="Print_Area"/></Cell>
    <Cell ss:Formula="=R[-1]C+1"><Data ss:Type="Number">33</Data></Cell>
    <Cell ss:Formula="=R[-1]C+1"><Data ss:Type="Number">34</Data></Cell>
   </Row>
  </Table>
  <WorksheetOptions xmlns="urn:schemas-microsoft-com:office:excel">
   <Unsynced/>
   <Print>
    <ValidPrinterInfo/>
    <HorizontalResolution>600</HorizontalResolution>
    <VerticalResolution>600</VerticalResolution>
   </Print>
   <Selected/>
   <FreezePanes/>
   <FrozenNoSplit/>
   <SplitHorizontal>2</SplitHorizontal>
   <TopRowBottomPane>2</TopRowBottomPane>
   <SplitVertical>1</SplitVertical>
   <LeftColumnRightPane>1</LeftColumnRightPane>
   <ActivePane>0</ActivePane>
   <Panes>
    <Pane>
     <Number>3</Number>
    </Pane>
    <Pane>
     <Number>1</Number>
    </Pane>
    <Pane>
     <Number>2</Number>
     <ActiveRow>5</ActiveRow>
    </Pane>
    <Pane>
     <Number>0</Number>
     <ActiveRow>5</ActiveRow>
    </Pane>
   </Panes>
   <ProtectObjects>False</ProtectObjects>
   <ProtectScenarios>False</ProtectScenarios>
   <x:ViewableRange>R1:R262144</x:ViewableRange>
   <x:Selection>R1C1</x:Selection>
  </WorksheetOptions>
  <c:WorksheetOptions>   </c:WorksheetOptions>
 </Worksheet>
 <Worksheet ss:Name="Sheet2">
  <Names>
   <NamedRange ss:Name="Print_Area" ss:RefersTo="=Sheet2!R3C2:R22C7"/>
   <NamedRange ss:Name="Print_Titles" ss:RefersTo="=Sheet2!C1,Sheet2!R2:R3"/>
  </Names>
  <WorksheetOptions xmlns="urn:schemas-microsoft-com:office:excel">
   <Print>
    <ValidPrinterInfo/>
    <HorizontalResolution>600</HorizontalResolution>
    <VerticalResolution>600</VerticalResolution>
   </Print>
   <ProtectObjects>False</ProtectObjects>
   <ProtectScenarios>False</ProtectScenarios>
   <x:ViewableRange>R1:R262144</x:ViewableRange>
   <x:Selection>R1C1</x:Selection>
  </WorksheetOptions>
  <c:WorksheetOptions>   </c:WorksheetOptions>
 </Worksheet>
 <Worksheet ss:Name="Sheet3">
  <WorksheetOptions xmlns="urn:schemas-microsoft-com:office:excel">
   <ProtectObjects>False</ProtectObjects>
   <ProtectScenarios>False</ProtectScenarios>
   <x:ViewableRange>R1:R262144</x:ViewableRange>
   <x:Selection>R1C1</x:Selection>
  </WorksheetOptions>
  <c:WorksheetOptions>   </c:WorksheetOptions>
 </Worksheet>
 <c:ComponentOptions>
   <c:Label>
    <c:Caption>Microsoft Office Spreadsheet</c:Caption>
   </c:Label>
   <c:MaxHeight>80%</c:MaxHeight>
   <c:MaxWidth>80%</c:MaxWidth>
   <c:NextSheetNumber>1</c:NextSheetNumber>
  </c:ComponentOptions>
 <x:WorkbookOptions>
   <c:OWCVersion>11.0.0.5531         </c:OWCVersion>
  </x:WorkbookOptions>
</Workbook>
